veimagex_mcp/__init__.py
veimagex_mcp/cli.py
veimagex_mcp/mcp_extend.py
veimagex_mcp/mcp_server.py
veimagex_mcp/note.py
veimagex_mcp/api/__init__.py
veimagex_mcp/api/config.py
veimagex_mcp/api/imagex.py
veimagex_mcp/utils/__init__.py
veimagex_mcp/utils/response.py
veimagex_mcp-0.1.5.dist-info/licenses/LICENSE.txt
veimagex_mcp-0.1.5.dist-info/METADATA
veimagex_mcp-0.1.5.dist-info/WHEEL
veimagex_mcp-0.1.5.dist-info/entry_points.txt
veimagex_mcp-0.1.5.dist-info/top_level.txt
veimagex_mcp-0.1.5.dist-info/RECORD
